rebrandly/__init__.py
rebrandly-0.0.4.dist-info/LICENSE
rebrandly-0.0.4.dist-info/METADATA
rebrandly-0.0.4.dist-info/WHEEL
rebrandly-0.0.4.dist-info/top_level.txt
rebrandly-0.0.4.dist-info/RECORD
