Metadata-Version: 2.1
Name: rebrandly
Version: 0.0.4
Summary: My short description for my project.
Home-page: https://github.com/franceme/rebrandly
Author: Miles Frantz
Author-email: frantzme@vt.edu
Classifier: Programming Language :: Python
Classifier: Programming Language :: Python :: 3
Classifier: Programming Language :: Python :: 3.8
Requires-Python: >=3.8.0
License-File: LICENSE
Requires-Dist: requests
